svs/__init__.py
svs/core.py
svs/logger.py
svs/scheduler.py
svs/security.py
svs/state_vector.py
svs/svs.py
svs/svs_base.py
svs/svs_thread.py
svs/svs_thread_base.py
svs/tlv.py
ndn_python_svs-0.1.2.dist-info/AUTHORS.rst
ndn_python_svs-0.1.2.dist-info/LICENSE.rst
ndn_python_svs-0.1.2.dist-info/METADATA
ndn_python_svs-0.1.2.dist-info/WHEEL
ndn_python_svs-0.1.2.dist-info/RECORD
