Metadata-Version: 2.1
Name: ndn-python-svs
Version: 0.1.2
Summary: NDN SVS package for Hydra
Author: See Authors.rst
Requires-Python: >=3.10,<4.0
Classifier: Programming Language :: Python :: 3
Classifier: Programming Language :: Python :: 3.10
Classifier: Programming Language :: Python :: 3.11
Classifier: Programming Language :: Python :: 3.12
Requires-Dist: ndn-lvs-envelope (>=0.1.1,<0.2.0)
Requires-Dist: ndn-storage (>=0.2.3,<0.3.0)
